{
    "powersupply": [
        {
            "PhwebDescription": "ACADPT 65 Watt nPFC USB-C",
            "ContainerValue": "HP 65 W USB Type-C™ adapter"
        },
        {
            "PhwebDescription": "ACADPT 65 Watt Smart nPFC",
            "ContainerValue": "65 W external power adapter, up to 89% efficiency"
        },
        {
            "PhwebDescription": "ACADPT 65W SLM USB-C Str",
            "ContainerValue": "65 W USB Type-C™ adapter"
        },
        {
            "PhwebDescription": "ACADPT 45 Watt Smart nPFC RA",
            "ContainerValue": "HP Smart 45 W External AC power adapter"
        },
        {
            "PhwebDescription": "ACADPT 45 Watt nPFC USB-C",
            "ContainerValue": "45 W USB Type-C™ adapter"
        },
        {
            "PhwebDescription": "P/S 180W ENT20",
            "ContainerValue": "180 W external power adapter, up to 90% efficiency, active PFC"
        },
        {
            "PhwebDescription": "ACADPT 45 Watt nPFC USB-C",
            "ContainerValue": "HP 45 W USB Type-C™ adapter"
        },
        {
            "PhwebDescription": "ACADPT 120 Watt Smart PFC Slim",
            "ContainerValue": "120 W external power adapter, up to 88% efficiency, active PFC"
        },
        {
            "PhwebDescription": "ACADPT 65 Watt nPFC USB-C",
            "ContainerValue": "65 W USB Type-C™ adapter"
        },
        {
            "PhwebDescription": "ACADPT 200W SLM4.5mmPFCRtAngSmt",
            "ContainerValue": "200 W external AC power adapter"
        },
        {
            "PhwebDescription": "ACADPT 150 Watt Smart PFC Slim",
            "ContainerValue": "150 W external power adapter, up to 89% efficiency, active PFC"
        },
        {
            "PhwebDescription": "ACADPT 65 Watt Smart nPFC EM",
            "ContainerValue": "65 W external power adapter, up to 89% efficiency"
        },
        {
            "PhwebDescription": "CHAS G9 280 MT 180W",
            "ContainerValue": "180 W external AC power adapter"
        },
        {
            "PhwebDescription": "ACADPT 90 Watt Smart PFC",
            "ContainerValue": "90 W external power adapter, up to 89% efficiency, active PFC"
        },
        {
            "PhwebDescription": "ACADPT100W+10WSLMUSB-C+USB-AStr",
            "ContainerValue": "100 W external AC power adapter"
        },
        {
            "PhwebDescription": "ACADPT 150W SLM4.5mmPFCRtAngSmt",
            "ContainerValue": "150 W external AC power adapter"
        },
        {
            "PhwebDescription": "ACADPT 180 Watt Smart PFC Slim",
            "ContainerValue": "180 W external AC power adapter"
        },
        {
            "PhwebDescription": "ACADPT 65 Watt Smart nPFC RA",
            "ContainerValue": "HP Smart 65 W External AC power adapter"
        },
        {
            "PhwebDescription": "P/S 180W SFF FY22",
            "ContainerValue": "180 W internal power supply, up to 90% efficiency, active PFC"
        },
        {
            "PhwebDescription": "P/S 180W TWR FY22",
            "ContainerValue": "180 W external AC power adapter"
        },
        {
            "PhwebDescription": "ACADPT 280W STD 7.4mm PFCStrSmt",
            "ContainerValue": "280 W external power adapter, up to 90% efficiency, active PFC"
        },
        {
            "PhwebDescription": "65 Watt DM Ext Power Adtr EPS",
            "ContainerValue": "65 W external power adapter, up to 89% efficiency"
        }
    ]
}